lark_sheet_mcp/__init__.py
lark_sheet_mcp/__main__.py
lark_sheet_mcp/config.py
lark_sheet_mcp/main.py
lark_sheet_mcp/server.py
lark_sheet_mcp/models/__init__.py
lark_sheet_mcp/models/data_models.py
lark_sheet_mcp/models/error_handling.py
lark_sheet_mcp/services/__init__.py
lark_sheet_mcp/services/api_client.py
lark_sheet_mcp/services/auth_manager.py
lark_sheet_mcp/tools/__init__.py
lark_sheet_mcp/tools/spreadsheet_tools.py
lark_sheet_mcp-1.0.1.dist-info/licenses/LICENSE
lark_sheet_mcp-1.0.1.dist-info/METADATA
lark_sheet_mcp-1.0.1.dist-info/WHEEL
lark_sheet_mcp-1.0.1.dist-info/entry_points.txt
lark_sheet_mcp-1.0.1.dist-info/top_level.txt
lark_sheet_mcp-1.0.1.dist-info/RECORD
