Metadata-Version: 2.4
Name: lark-sheet-mcp
Version: 1.0.1
Summary: A Model Context Protocol (MCP) server for accessing Feishu/Lark spreadsheet data
Home-page: https://github.com/lupin/lark-sheet-mcp
Author: Lupin
Author-email: Lupin <lupin@example.com>
License: MIT
Project-URL: Homepage, https://github.com/lupin/lark-sheet-mcp
Project-URL: Repository, https://github.com/lupin/lark-sheet-mcp
Project-URL: Issues, https://github.com/lupin/lark-sheet-mcp/issues
Project-URL: Documentation, https://github.com/lupin/lark-sheet-mcp#readme
Keywords: feishu,lark,spreadsheet,mcp,model-context-protocol,api
Classifier: Development Status :: 4 - Beta
Classifier: Intended Audience :: Developers
Classifier: License :: OSI Approved :: MIT License
Classifier: Operating System :: OS Independent
Classifier: Programming Language :: Python :: 3
Classifier: Programming Language :: Python :: 3.8
Classifier: Programming Language :: Python :: 3.9
Classifier: Programming Language :: Python :: 3.10
Classifier: Programming Language :: Python :: 3.11
Classifier: Programming Language :: Python :: 3.12
Classifier: Topic :: Software Development :: Libraries :: Python Modules
Classifier: Topic :: Office/Business :: Financial :: Spreadsheet
Classifier: Topic :: Internet :: WWW/HTTP :: Dynamic Content
Requires-Python: >=3.8
License-File: LICENSE
Requires-Dist: fastmcp>=0.9.0
Requires-Dist: pydantic>=2.0.0
Requires-Dist: python-dotenv>=1.0.0
Requires-Dist: aiohttp>=3.8.0
Provides-Extra: dev
Requires-Dist: pytest>=7.0.0; extra == "dev"
Requires-Dist: pytest-asyncio>=0.21.0; extra == "dev"
Requires-Dist: pytest-cov>=4.0.0; extra == "dev"
Requires-Dist: black>=23.0.0; extra == "dev"
Requires-Dist: flake8>=6.0.0; extra == "dev"
Requires-Dist: mypy>=1.0.0; extra == "dev"
Requires-Dist: isort>=5.12.0; extra == "dev"
Requires-Dist: pytest-mock>=3.10.0; extra == "dev"
Requires-Dist: responses>=0.23.0; extra == "dev"
Dynamic: author
Dynamic: home-page
Dynamic: license-file
Dynamic: requires-python
